{
	"info": {
		"_postman_id": "626aa8da-eb9c-4ef4-9d77-a9a7e77e35f4",
		"name": "Ventas",
		"schema": "https://schema.getpostman.com/json/collection/v2.1.0/collection.json"
	},
	"item": [
		{
			"name": "agregarUsuario",
			"request": {
				"method": "POST",
				"header": [],
				"body": {
					"mode": "urlencoded",
					"urlencoded": [
						{
							"key": "nombre",
							"value": "Noel",
							"type": "text"
						},
						{
							"key": "username",
							"value": "anoel",
							"type": "text"
						},
						{
							"key": "password",
							"value": "123456",
							"type": "text"
						}
					]
				},
				"url": {
					"raw": "localhost:3000/api/agregarUsuario",
					"host": [
						"localhost"
					],
					"port": "3000",
					"path": [
						"api",
						"agregarUsuario"
					]
				}
			},
			"response": []
		},
		{
			"name": "login",
			"request": {
				"method": "POST",
				"header": [],
				"body": {
					"mode": "urlencoded",
					"urlencoded": [
						{
							"key": "username",
							"value": "Admin",
							"type": "text"
						},
						{
							"key": "password",
							"value": "123456",
							"type": "text"
						},
						{
							"key": "getToken",
							"value": "true",
							"type": "text"
						}
					]
				},
				"url": {
					"raw": "localhost:3000/api/login",
					"host": [
						"localhost"
					],
					"port": "3000",
					"path": [
						"api",
						"login"
					]
				}
			},
			"response": []
		},
		{
			"name": "editarUsuario",
			"request": {
				"method": "PUT",
				"header": [
					{
						"key": "Authorization",
						"value": "eyJ0eXAiOiJKV1QiLCJhbGciOiJIUzI1NiJ9.eyJzdWIiOiI2MDRjM2UwMTRjNzI1YjBiMTQxNDQyZTMiLCJub21icmUiOiJOb2VsIiwidXNlcm5hbWUiOiJhbm9lbCIsInJvbCI6IlJPTF9DTElFTlRFIiwiaWF0IjoxNjE1NjA5NDYzLCJleHAiOjE2MTYwNDE0NjN9.G7cQ_D9gaPBd7QzxT4UaegvVqhHesy5iOsGZRh-pWF0",
						"type": "text"
					}
				],
				"body": {
					"mode": "urlencoded",
					"urlencoded": [
						{
							"key": "nombre",
							"value": "Brenton",
							"type": "text"
						},
						{
							"key": "username",
							"value": "blopez",
							"type": "text"
						}
					]
				},
				"url": {
					"raw": "localhost:3000/api/editarUsuario",
					"host": [
						"localhost"
					],
					"port": "3000",
					"path": [
						"api",
						"editarUsuario"
					]
				}
			},
			"response": []
		},
		{
			"name": "eliminarUsuario",
			"request": {
				"method": "DELETE",
				"header": [
					{
						"key": "Authorization",
						"value": "eyJ0eXAiOiJKV1QiLCJhbGciOiJIUzI1NiJ9.eyJzdWIiOiI2MDRjM2UwMTRjNzI1YjBiMTQxNDQyZTMiLCJub21icmUiOiJOb2VsIiwidXNlcm5hbWUiOiJhbm9lbCIsInJvbCI6IlJPTF9DTElFTlRFIiwiaWF0IjoxNjE1NjA5NDYzLCJleHAiOjE2MTYwNDE0NjN9.G7cQ_D9gaPBd7QzxT4UaegvVqhHesy5iOsGZRh-pWF0",
						"type": "text"
					}
				],
				"body": {
					"mode": "urlencoded",
					"urlencoded": []
				},
				"url": {
					"raw": "localhost:3000/api/eliminarUsuario",
					"host": [
						"localhost"
					],
					"port": "3000",
					"path": [
						"api",
						"eliminarUsuario"
					]
				}
			},
			"response": []
		},
		{
			"name": "agregarCategoria",
			"request": {
				"method": "POST",
				"header": [
					{
						"key": "Authorization",
						"value": "eyJ0eXAiOiJKV1QiLCJhbGciOiJIUzI1NiJ9.eyJzdWIiOiI2MDRjM2Q5ZmUxNDA1ZTMwZjgyZjMwN2EiLCJub21icmUiOiJBZG1pbmlzdHJhZG9yIiwidXNlcm5hbWUiOiJBZG1pbiIsInJvbCI6IlJPTF9BRE1JTiIsImlhdCI6MTYxNTYwOTk1MiwiZXhwIjoxNjE2MDQxOTUyfQ.HD0LPiGLLe7CvlYzWBFk9pa_6H3AS6iFA-GGyNibzAc",
						"type": "text"
					}
				],
				"body": {
					"mode": "urlencoded",
					"urlencoded": [
						{
							"key": "nombre",
							"value": "Libreria",
							"type": "text"
						}
					]
				},
				"url": {
					"raw": "localhost:3000/api/agregarCategoria",
					"host": [
						"localhost"
					],
					"port": "3000",
					"path": [
						"api",
						"agregarCategoria"
					]
				}
			},
			"response": []
		},
		{
			"name": "eliminarCategoria",
			"request": {
				"method": "DELETE",
				"header": [
					{
						"key": "Authorization",
						"value": "eyJ0eXAiOiJKV1QiLCJhbGciOiJIUzI1NiJ9.eyJzdWIiOiI2MDRjM2Q5ZmUxNDA1ZTMwZjgyZjMwN2EiLCJub21icmUiOiJBZG1pbmlzdHJhZG9yIiwidXNlcm5hbWUiOiJBZG1pbiIsInJvbCI6IlJPTF9BRE1JTiIsImlhdCI6MTYxNTYwOTk1MiwiZXhwIjoxNjE2MDQxOTUyfQ.HD0LPiGLLe7CvlYzWBFk9pa_6H3AS6iFA-GGyNibzAc",
						"type": "text"
					}
				],
				"url": {
					"raw": "localhost:3000/api/eliminarCategoria/:id",
					"host": [
						"localhost"
					],
					"port": "3000",
					"path": [
						"api",
						"eliminarCategoria",
						":id"
					],
					"variable": [
						{
							"key": "id",
							"value": ""
						}
					]
				}
			},
			"response": []
		},
		{
			"name": "editarCategoria",
			"request": {
				"method": "PUT",
				"header": [
					{
						"key": "Authorization",
						"value": "eyJ0eXAiOiJKV1QiLCJhbGciOiJIUzI1NiJ9.eyJzdWIiOiI2MDRjM2Q5ZmUxNDA1ZTMwZjgyZjMwN2EiLCJub21icmUiOiJBZG1pbmlzdHJhZG9yIiwidXNlcm5hbWUiOiJBZG1pbiIsInJvbCI6IlJPTF9BRE1JTiIsImlhdCI6MTYxNTYwOTk1MiwiZXhwIjoxNjE2MDQxOTUyfQ.HD0LPiGLLe7CvlYzWBFk9pa_6H3AS6iFA-GGyNibzAc",
						"type": "text"
					}
				],
				"body": {
					"mode": "urlencoded",
					"urlencoded": [
						{
							"key": "nombre",
							"value": "Electrodomesticos",
							"type": "text"
						}
					]
				},
				"url": {
					"raw": "localhost:3000/api/editarCategoria/:id",
					"host": [
						"localhost"
					],
					"port": "3000",
					"path": [
						"api",
						"editarCategoria",
						":id"
					],
					"variable": [
						{
							"key": "id",
							"value": ""
						}
					]
				}
			},
			"response": []
		},
		{
			"name": "obtenerCategorias",
			"protocolProfileBehavior": {
				"disableBodyPruning": true
			},
			"request": {
				"method": "GET",
				"header": [],
				"body": {
					"mode": "urlencoded",
					"urlencoded": []
				},
				"url": {
					"raw": "localhost:3000/api/obtenerCategorias",
					"host": [
						"localhost"
					],
					"port": "3000",
					"path": [
						"api",
						"obtenerCategorias"
					]
				}
			},
			"response": []
		},
		{
			"name": "agregarProducto",
			"request": {
				"method": "POST",
				"header": [
					{
						"key": "Authorization",
						"value": "eyJ0eXAiOiJKV1QiLCJhbGciOiJIUzI1NiJ9.eyJzdWIiOiI2MDRjM2Q5ZmUxNDA1ZTMwZjgyZjMwN2EiLCJub21icmUiOiJBZG1pbmlzdHJhZG9yIiwidXNlcm5hbWUiOiJBZG1pbiIsInJvbCI6IlJPTF9BRE1JTiIsImlhdCI6MTYxNTYwOTk1MiwiZXhwIjoxNjE2MDQxOTUyfQ.HD0LPiGLLe7CvlYzWBFk9pa_6H3AS6iFA-GGyNibzAc",
						"type": "text"
					}
				],
				"body": {
					"mode": "urlencoded",
					"urlencoded": [
						{
							"key": "nombre",
							"value": "Licuadora",
							"type": "text"
						},
						{
							"key": "precio",
							"value": "500",
							"type": "text"
						},
						{
							"key": "cantidad",
							"value": "0",
							"type": "text"
						},
						{
							"key": "idCategoria",
							"value": "604c416b4c725b0b141442e5",
							"type": "text"
						}
					]
				},
				"url": {
					"raw": "localhost:3000/api/agregarProducto",
					"host": [
						"localhost"
					],
					"port": "3000",
					"path": [
						"api",
						"agregarProducto"
					]
				}
			},
			"response": []
		},
		{
			"name": "editarProducto",
			"request": {
				"method": "PUT",
				"header": [
					{
						"key": "Authorization",
						"value": "eyJ0eXAiOiJKV1QiLCJhbGciOiJIUzI1NiJ9.eyJzdWIiOiI2MDRjM2Q5ZmUxNDA1ZTMwZjgyZjMwN2EiLCJub21icmUiOiJBZG1pbmlzdHJhZG9yIiwidXNlcm5hbWUiOiJBZG1pbiIsInJvbCI6IlJPTF9BRE1JTiIsImlhdCI6MTYxNTYwOTk1MiwiZXhwIjoxNjE2MDQxOTUyfQ.HD0LPiGLLe7CvlYzWBFk9pa_6H3AS6iFA-GGyNibzAc",
						"type": "text"
					}
				],
				"body": {
					"mode": "urlencoded",
					"urlencoded": [
						{
							"key": "nombre",
							"value": "Lavadora",
							"type": "text"
						}
					]
				},
				"url": {
					"raw": "localhost:3000/api/editarProducto/:id",
					"host": [
						"localhost"
					],
					"port": "3000",
					"path": [
						"api",
						"editarProducto",
						":id"
					],
					"variable": [
						{
							"key": "id",
							"value": "604c437d4c725b0b141442e7"
						}
					]
				}
			},
			"response": []
		},
		{
			"name": "eliminarProducto",
			"request": {
				"method": "DELETE",
				"header": [
					{
						"key": "Authorization",
						"value": "eyJ0eXAiOiJKV1QiLCJhbGciOiJIUzI1NiJ9.eyJzdWIiOiI2MDRjM2Q5ZmUxNDA1ZTMwZjgyZjMwN2EiLCJub21icmUiOiJBZG1pbmlzdHJhZG9yIiwidXNlcm5hbWUiOiJBZG1pbiIsInJvbCI6IlJPTF9BRE1JTiIsImlhdCI6MTYxNTYwOTk1MiwiZXhwIjoxNjE2MDQxOTUyfQ.HD0LPiGLLe7CvlYzWBFk9pa_6H3AS6iFA-GGyNibzAc",
						"type": "text"
					}
				],
				"body": {
					"mode": "urlencoded",
					"urlencoded": []
				},
				"url": {
					"raw": "localhost:3000/api/eliminarProducto/:id",
					"host": [
						"localhost"
					],
					"port": "3000",
					"path": [
						"api",
						"eliminarProducto",
						":id"
					],
					"variable": [
						{
							"key": "id",
							"value": "604c437d4c725b0b141442e7"
						}
					]
				}
			},
			"response": []
		},
		{
			"name": "obtenerProductos",
			"protocolProfileBehavior": {
				"disableBodyPruning": true
			},
			"request": {
				"method": "GET",
				"header": [],
				"body": {
					"mode": "urlencoded",
					"urlencoded": []
				},
				"url": {
					"raw": "localhost:3000/api/obtenerProductos",
					"host": [
						"localhost"
					],
					"port": "3000",
					"path": [
						"api",
						"obtenerProductos"
					]
				}
			},
			"response": []
		},
		{
			"name": "obtenerProductosCategoria",
			"request": {
				"method": "GET",
				"header": [],
				"url": {
					"raw": "localhost:3000/api/obtenerProductosCategoria/:id",
					"host": [
						"localhost"
					],
					"port": "3000",
					"path": [
						"api",
						"obtenerProductosCategoria",
						":id"
					],
					"variable": [
						{
							"key": "id",
							"value": "604c416b4c725b0b141442e5"
						}
					]
				}
			},
			"response": []
		},
		{
			"name": "obtenerPorNombre",
			"protocolProfileBehavior": {
				"disableBodyPruning": true
			},
			"request": {
				"method": "GET",
				"header": [],
				"body": {
					"mode": "urlencoded",
					"urlencoded": [
						{
							"key": "nombre",
							"value": "Licuadora",
							"type": "text"
						}
					]
				},
				"url": {
					"raw": "localhost:3000/api/obtenerPorNombre",
					"host": [
						"localhost"
					],
					"port": "3000",
					"path": [
						"api",
						"obtenerPorNombre"
					]
				}
			},
			"response": []
		},
		{
			"name": "obtenerAgotados",
			"protocolProfileBehavior": {
				"disableBodyPruning": true
			},
			"request": {
				"method": "GET",
				"header": [],
				"body": {
					"mode": "urlencoded",
					"urlencoded": []
				},
				"url": {
					"raw": "localhost:3000/api/obtenerAgotados",
					"host": [
						"localhost"
					],
					"port": "3000",
					"path": [
						"api",
						"obtenerAgotados"
					]
				}
			},
			"response": []
		}
	]
}